{
  "type": "FeatureCollection",
  "geocoding": {
    "version": "0.1.0",
    "attribution": "Data © OpenStreetMap contributors, ODbL 1.0. http://osm.org/copyright",
    "licence": "ODbL",
    "query": "Комсомольск, Россия"
  },
  "features": [
    {
      "type": "Feature",
      "properties": {
        "geocoding": {
          "place_id": 184657996,
          "osm_type": "relation",
          "osm_id": 3443037,
          "osm_key": "place",
          "osm_value": "town",
          "type": "city",
          "label": "Комсомольск, Комсомольское городское поселение, Комсомольский район, Ивановская область, Центральный федеральный округ, 155150, Россия",
          "name": "Комсомольск",
          "postcode": "155150",
          "city": "Комсомольское городское поселение",
          "county": "Комсомольский район",
          "state": "Ивановская область",
          "country": "Россия",
          "country_code": "ru",
          "admin": {
            "level8": "Комсомольское городское поселение",
            "level6": "Комсомольский район",
            "level4": "Ивановская область",
            "level3": "Центральный федеральный округ"
          },
          "extra": {
            "wikidata": "Q154785",
            "wikipedia": "ru:Комсомольск (Ивановская область)",
            "population": "8561",
            "linked_place": "town",
            "official_status": "ru:город",
            "population:date": "2015-01-01"
          }
        }
      },
      "geometry": {
        "type": "Polygon",
        "coordinates": [
          [
            [
              40.3492986,
              57.0499608
            ],
            [
              40.3510155,
              57.0467748
            ],
            [
              40.3635382,
              57.0435335
            ],
            [
              40.366265,
              57.0386986
            ],
            [
              40.3638412,
              57.0351269
            ],
            [
              40.3586907,
              57.035017
            ],
            [
              40.3582868,
              57.032709
            ],
            [
              40.3535402,
              57.0321045
            ],
            [
              40.3540452,
              57.0270482
            ],
            [
              40.3573778,
              57.0254543
            ],
            [
              40.3700016,
              57.0222661
            ],
            [
              40.3716859,
              57.0210125
            ],
            [
              40.3733343,
              57.0152293
            ],
            [
              40.3708095,
              57.0120402
            ],
            [
              40.3730313,
              57.0106656
            ],
            [
              40.3792927,
              57.0131399
            ],
            [
              40.386564,
              57.0104456
            ],
            [
              40.3931283,
              57.0123152
            ],
            [
              40.4042373,
              57.0127551
            ],
            [
              40.40656,
              57.0115454
            ],
            [
              40.4102145,
              57.0114725
            ],
            [
              40.4121081,
              57.0137406
            ],
            [
              40.4079422,
              57.0151839
            ],
            [
              40.4109719,
              57.0164897
            ],
            [
              40.4095833,
              57.021781
            ],
            [
              40.3980716,
              57.0238826
            ],
            [
              40.3996373,
              57.0332716
            ],
            [
              40.3935483,
              57.0369989
            ],
            [
              40.3935152,
              57.0400957
            ],
            [
              40.3885844,
              57.04141
            ],
            [
              40.3881798,
              57.0427094
            ],
            [
              40.3835343,
              57.0443576
            ],
            [
              40.3808075,
              57.0477636
            ],
            [
              40.3725264,
              57.0445773
            ],
            [
              40.3649521,
              57.0463353
            ],
            [
              40.3543481,
              57.0497411
            ],
            [
              40.3492986,
              57.0499608
            ]
          ]
        ]
      }
    }
  ]
}